watson/__init__.py
watson/assets/__init__.py
watson/assets/globals.py
watson/assets/webpack/__init__.py
watson/assets/webpack/exceptions.py
watson/assets/webpack/jinja2.py
watson_assets-1.0.7.dist-info/DESCRIPTION.rst
watson_assets-1.0.7.dist-info/METADATA
watson_assets-1.0.7.dist-info/RECORD
watson_assets-1.0.7.dist-info/WHEEL
watson_assets-1.0.7.dist-info/metadata.json
watson_assets-1.0.7.dist-info/top_level.txt
