Metadata-Version: 2.0
Name: watson-assets
Version: 1.0.7
Summary: Manage publicly available assets within your application.
Home-page: http://github.com/watsonpy/watson-assets
Author: Simon Coulton
Author-email: simon@bespohk.com
License: Copyright (c) 2012-2016 Bespohk, and is maintained by multiple
Requires-Dist: watson-common (>=1.4.2)
Provides-Extra: test
Requires-Dist: coverage; extra == 'test'
Requires-Dist: coveralls; extra == 'test'
Requires-Dist: pytest; extra == 'test'
Requires-Dist: pytest-cov; extra == 'test'
